core.py
testnurmuhammad-0.0.0.3.dist-info/METADATA
testnurmuhammad-0.0.0.3.dist-info/WHEEL
testnurmuhammad-0.0.0.3.dist-info/top_level.txt
testnurmuhammad-0.0.0.3.dist-info/RECORD
