Metadata-Version: 2.4
Name: testNurmuhammad
Version: 0.0.0.3
Summary: My example package
Author: Nurmuhammad Hasanov
Author-email: nurmuhammad@example.com
Dynamic: author
Dynamic: author-email
Dynamic: summary
